{
  "project_info": {
    "project_number": "571495207196",
    "project_id": "hoangnv10052004",
    "storage_bucket": ""
  },
  "client": [
    {
      "client_info": {
        "mobilesdk_app_id": "1:571495207196:android:0000000000000001",
        "android_client_info": {
          "package_name": "com.example.flutterfashion"
        }
      },
      "oauth_client": [
        {
          "client_id": "571495207196-f82d645pgame7788vemfk3bi2iuhr0m0.apps.googleusercontent.com",
          "client_type": 1,
          "android_info": {
            "package_name": "com.example.flutterfashion",
            "certificate_hash": "e058dde7f568eb46204f9b5db5dc4f7beee07a55"
          }
        },
        {
          "client_id": "571495207196-1ggrpkpdbpflu58qnbi8b00iqvusg312.apps.googleusercontent.com",
          "client_type": 3
        }
      ],
      "api_key": [
        {
          "current_key": ""
        }
      ],
      "services": {
        "appinvite_service": {
          "other_platform_oauth_client": [
            {
              "client_id": "571495207196-1ggrpkpdbpflu58qnbi8b00iqvusg312.apps.googleusercontent.com",
              "client_type": 3
            }
          ]
        }
      }
    }
  ],
  "configuration_version": "1"
}
